wsa_toetsing_tool/__init__.py
wsa_toetsing_tool/__version__.py
wsa_toetsing_tool/compensatie.py
wsa_toetsing_tool/config.py
wsa_toetsing_tool/dhydro_utils.py
wsa_toetsing_tool/helpers.py
wsa_toetsing_tool/his_utils.py
wsa_toetsing_tool/knelpunten.py
wsa_toetsing_tool/nc_utils.py
wsa_toetsing_tool/sobek_netwerk.py
wsa_toetsing_tool/toetsing.py
wsa_toetsing_tool/wsa.py
wsa_toetsing_tool/hkvsobekpy_wsa/__init__.py
wsa_toetsing_tool/hkvsobekpy_wsa/__main__.py
wsa_toetsing_tool/hkvsobekpy_wsa/core/__init__.py
wsa_toetsing_tool/hkvsobekpy_wsa/core/plausibility.py
wsa_toetsing_tool/hkvsobekpy_wsa/core/utils.py
wsa_toetsing_tool/hkvsobekpy_wsa/core/waterlevelstat.py
wsa_toetsing_tool/hkvsobekpy_wsa/io/__init__.py
wsa_toetsing_tool/hkvsobekpy_wsa/io/bui.py
wsa_toetsing_tool/hkvsobekpy_wsa/io/his.py
wsa_toetsing_tool-4.0.1.dist-info/LICENSE
wsa_toetsing_tool-4.0.1.dist-info/METADATA
wsa_toetsing_tool-4.0.1.dist-info/WHEEL
wsa_toetsing_tool-4.0.1.dist-info/top_level.txt
wsa_toetsing_tool-4.0.1.dist-info/RECORD
