Metadata-Version: 2.1
Name: wsa-toetsing-tool
Version: 4.0.1
Summary: Postprocessing tool voor WSA toetsing
Home-page: https://hhdelfland.visualstudio.com/Waterhuishouding/_git/WSA_toetsing_tool
Author: Emiel Verstegen
Author-email: emiel.verstegen@rhdhv.com
License: GPL-3.0
Platform: UNKNOWN
Classifier: Programming Language :: Python :: 3
Classifier: License :: OSI Approved :: GNU General Public License v3 (GPLv3)
Classifier: Operating System :: OS Independent
Requires-Python: >=3.6
License-File: LICENSE
Requires-Dist: rasterio==1.3.4
Requires-Dist: shapely==2.0.1
Requires-Dist: geopandas==0.12.2
Requires-Dist: pandas==1.5.3
Requires-Dist: xarray==2023.2.0
Requires-Dist: numpy==1.24.2
Requires-Dist: plotly==5.13.0
Requires-Dist: jupyterlab
Requires-Dist: scipy==1.10.0
Requires-Dist: gdal==3.6.2
Requires-Dist: fiona==1.9.1
Requires-Dist: ipywidgets==8.1.3
Requires-Dist: tqdm==4.66.4
Requires-Dist: pyyaml==6.0.1
Requires-Dist: matplotlib==3.8.4
Requires-Dist: netCDF4==1.6.2
Requires-Dist: setuptools==59.8
Requires-Dist: openpyxl==3.1.2
Requires-Dist: rasterstats==0.19.0
Requires-Dist: fire==0.6.0
Requires-Dist: rioxarray==0.15.5
Requires-Dist: pyarrow==17.0.0
Requires-Dist: pytest==7.4.3
Requires-Dist: pytest-ordering==0.6
